graffe/__init__.py
graffe/__main__.py
graffe/graph.py
graffe-0.1.0.dist-info/LICENSE
graffe-0.1.0.dist-info/METADATA
graffe-0.1.0.dist-info/WHEEL
graffe-0.1.0.dist-info/top_level.txt
graffe-0.1.0.dist-info/RECORD
