Metadata-Version: 2.1
Name: graffe
Version: 0.1.0
Summary: A desktop application to simplify graph creation for scientific, two-variable data.
Author-email: John Constable <johnmconstable@icloud.com>
License: GNU AFFERO GENERAL PUBLIC LICENSE
Project-URL: Homepage, https://github.com/ensanguinedIB/graffe
Project-URL: Bug Tracker, https://github.com/ensanguinedIB/graffe/issues
Classifier: Programming Language :: Python :: 3
Classifier: License :: OSI Approved :: GNU Affero General Public License v3
Classifier: Operating System :: OS Independent
Requires-Python: >=3.7
License-File: LICENSE
Requires-Dist: matplotlib
Requires-Dist: Pillow
